msconvert_cli/__init__.py
msconvert_cli/cli.py
msconvert_cli/converter.py
msconvert_cli/logging_config.py
msconvert_cli/presets.py
msconvert_cli/py.typed
msconvert_cli/configs/biosuar.txt
msconvert_cli/configs/blitzff.txt
msconvert_cli/configs/casanovo.txt
msconvert_cli/configs/casanovo_mgf.txt
msconvert_cli/configs/sage.txt
msconvert_cli-1.1.0.dist-info/METADATA
msconvert_cli-1.1.0.dist-info/WHEEL
msconvert_cli-1.1.0.dist-info/entry_points.txt
msconvert_cli-1.1.0.dist-info/licenses/LICENSE
msconvert_cli-1.1.0.dist-info/RECORD
