Metadata-Version: 2.4
Name: msconvert-cli
Version: 1.1.0
Summary: Python wrapper for ProteoWizard msconvert with Docker support and preset configs
Project-URL: Homepage, https://github.com/pgarrett-scripps/msconvert-cli
Project-URL: Repository, https://github.com/pgarrett-scripps/msconvert-cli
Project-URL: Documentation, https://pgarrett-scripps.github.io/msconvert-cli/
Project-URL: Issues, https://github.com/pgarrett-scripps/msconvert-cli/issues
Author-email: Patrick Garrett <pgarrett@scripps.edu>
License-File: LICENSE
Keywords: docker,mass-spectrometry,msconvert,proteomics,proteowizard
Classifier: Intended Audience :: Science/Research
Classifier: Programming Language :: Python
Classifier: Programming Language :: Python :: 3
Classifier: Programming Language :: Python :: 3.9
Classifier: Programming Language :: Python :: 3.10
Classifier: Programming Language :: Python :: 3.11
Classifier: Programming Language :: Python :: 3.12
Classifier: Programming Language :: Python :: 3.13
Classifier: Topic :: Scientific/Engineering :: Bio-Informatics
Requires-Python: <4.0,>=3.9
Requires-Dist: typing-extensions>=4.0.0
